valhallaAPI/__init__.py
valhallaAPI/filters.py
valhallaAPI/helper.py
valhallaAPI/valhalla.py
valhallaAPI/valhalla_cli.py
valhallaapi-0.6.2.dist-info/LICENSE
valhallaapi-0.6.2.dist-info/METADATA
valhallaapi-0.6.2.dist-info/WHEEL
valhallaapi-0.6.2.dist-info/entry_points.txt
valhallaapi-0.6.2.dist-info/top_level.txt
valhallaapi-0.6.2.dist-info/RECORD
