Metadata-Version: 2.1
Name: valhallaapi
Version: 0.6.2
Summary: Valhalla API Client
Home-page: https://github.com/NextronSystems/valhallaAPI
Author: Nextron
Author-email: florian.roth@nextron-systems.com
License: UNKNOWN
Platform: UNKNOWN
Classifier: Programming Language :: Python :: 3
Classifier: License :: OSI Approved :: Apache Software License
Classifier: Operating System :: OS Independent
Requires-Python: ~=3.5
License-File: LICENSE
